gtec_ble/__init__.py
gtec_ble/__version__.py
gtec_ble/amplifier.py
gtec_ble/__pyinstaller/__init__.py
gtec_ble/__pyinstaller/hook-gtec_ble.py
gtec_ble/lib/__init__.py
gtec_ble/lib/gtec_ble_wrapper.c
gtec_ble/lib/gtec_ble_wrapper.cpython-39-darwin.so
gtec_ble/lib/gtec_ble_wrapper.pyx
gtec_ble/lib/libpath.py
gtec_ble/lib/test.py
gtec_ble/lib/native/mac/arm64/libgtecble.dylib
gtec_ble/lib/native/mac/universal/libgtecble.dylib
gtec_ble/lib/native/windows/x64/libgtecble.dll
gtec_ble-2.0.1.dist-info/licenses/LICENSE
gtec_ble-2.0.1.dist-info/METADATA
gtec_ble-2.0.1.dist-info/WHEEL
gtec_ble-2.0.1.dist-info/entry_points.txt
gtec_ble-2.0.1.dist-info/top_level.txt
gtec_ble-2.0.1.dist-info/RECORD
