Metadata-Version: 2.4
Name: gtec-ble
Version: 2.0.1
Summary: A Bluetooth Low Energy (BLE) API. To be used only as part of g.Pype.
Home-page: https://www.gtec.at
Author: g.tec medical engineering GmbH
Author-email: support@gtec.at
License: g.tec Non-Commercial License (GNCL)
Classifier: Development Status :: 4 - Beta
Classifier: Operating System :: Microsoft :: Windows
Classifier: Operating System :: MacOS
Classifier: Programming Language :: Python :: 3
License-File: LICENSE
Requires-Dist: numpy>=1.14.4
Dynamic: author
Dynamic: author-email
Dynamic: classifier
Dynamic: description-content-type
Dynamic: home-page
Dynamic: license
Dynamic: license-file
Dynamic: requires-dist
Dynamic: summary
